{
    "sea @ det": {
        "cal raleigh": {
            "dk": "+240"
        },
        "colt keith": {
            "dk": "+425"
        },
        "spencer torkelson": {
            "dk": "+450"
        },
        "riley greene": {
            "dk": "+475"
        },
        "jorge polanco": {
            "dk": "+500"
        },
        "randy arozarena": {
            "dk": "+500"
        },
        "zach mckinstry": {
            "dk": "+600"
        },
        "matt vierling": {
            "dk": "+600"
        },
        "luke raley": {
            "dk": "+650"
        },
        "dillon dingler": {
            "dk": "+650"
        },
        "dominic canzone": {
            "dk": "+650"
        },
        "gleyber torres": {
            "dk": "+700"
        },
        "julio rodriguez": {
            "dk": "+700"
        },
        "javier baez": {
            "dk": "+800"
        },
        "parker meadows": {
            "dk": "+850"
        },
        "jp crawford": {
            "dk": "+950"
        },
        "ben williamson": {
            "dk": "+1700"
        },
        "cole young": {
            "dk": "+1800"
        }
    },
    "mia @ bal": {
        "jordan westburg": {
            "dk": "+340"
        },
        "gunnar henderson": {
            "dk": "+360"
        },
        "colton cowser": {
            "dk": "+390"
        },
        "tyler oneill": {
            "dk": "+425"
        },
        "jackson holliday": {
            "dk": "+450"
        },
        "ryan ohearn": {
            "dk": "+450"
        },
        "cedric mullins": {
            "dk": "+450"
        },
        "ramon laureano": {
            "dk": "+475"
        },
        "jacob stallings": {
            "dk": "+850"
        }
    },
    "chc @ nyy": {
        "kyle tucker": {
            "dk": "+400"
        },
        "seiya suzuki": {
            "dk": "+475"
        },
        "michael busch": {
            "dk": "+550"
        },
        "pete crow armstrong": {
            "dk": "+550"
        },
        "dansby swanson": {
            "dk": "+600"
        },
        "carson kelly": {
            "dk": "+650"
        },
        "ian happ": {
            "dk": "+650"
        },
        "nico hoerner": {
            "dk": "+1100"
        },
        "jon berti": {
            "dk": "+1500"
        }
    },
    "tb @ bos": {
        "yandy diaz": {
            "dk": "+500"
        },
        "junior caminero": {
            "dk": "+550"
        },
        "christopher morel": {
            "dk": "+600"
        },
        "danny jansen": {
            "dk": "+650"
        },
        "ha seong kim": {
            "dk": "+900"
        },
        "jose caballero": {
            "dk": "+1000"
        },
        "curtis mead": {
            "dk": "+1100"
        },
        "taylor walls": {
            "dk": "+1200"
        },
        "jake mangum": {
            "dk": "+1300"
        }
    }
}